{
  "users": [
    {
      "id": 1,
      "username": "d_j2005",
      "fullName": "Divya Jenifer",
      "profilePicture": "public/assets/profile1.jpeg",
      "bio": "Photography lover 📸 | Traveler ✈️ | Foodie 🍕",
      "followers": 1200,
      "following": 300,
      "posts": [
        {
          "id": 101,
          "image": "public/assets/profile3.jpg",
          "caption": "Matching with the Roses #flower #nature",
          "likes": 350,
          "comments": [
            { "id": 1, "user": "friend_01", "comment": "Wow, amazing view!" },
            { "id": 2, "user": "friend_02", "comment": "I want to go there too!" }
          ],
          "createdAt": "2025-11-19T10:30:00Z"
        }
          ]
    },
    {
      "id": 2,
      "username": "alexa_rider",
      "fullName": "Alexa Rider",
      "profilePicture": "public/assets/profile2.jpeg",
      "bio": "Adventure seeker 🏔️ | Coffee addict ☕ | Blogger",
      "followers": 900,
      "following": 400,
      "posts": [
        {
          "id": 201,
          "image": "public/assets/sunset.jpg",
          "caption": "Sunset by the lake 🌅 #nature",
          "likes": 420,
          "comments": [
            { "id": 4, "user": "divya_jenifer", "comment": "Stunning colors!" }
          ],
          "createdAt": "2025-11-19T07:20:00Z"
        }
        
      ]
    },
    {
      "id": 3,
      "username": "@iambeingsarcastic",
      "fullName": "sarcasim",
      "profilePicture": "public/assets/noprofile.jpg",
      "bio": "blast",
      "followers": 1200,
      "following": 300,
      "posts": [
        {
          "id": 301,
          "image": "public/assets/memepost2.jpeg",
          "caption": "not so cute📸:)",
          "likes": 350,
          "comments": [
            { "id": 1, "user": "friend_01", "comment": "Wow, amazing view!" },
            { "id": 2, "user": "friend_02", "comment": "I want to go there too!" }
          ],
          "createdAt": "2025-11-19T10:30:00Z"
        }
          ]
    },
    {
      "id": 4,
      "username": "Suriya.rolex_1980",
      "fullName": "Suriya",
      "profilePicture": "public/assets/newprofile1.jpeg",
      "bio": "Photography lover 📸 | Traveler ✈️ | Foodie 🍕",
      "followers": 1200,
      "following": 300,
      "posts": [
        {
          "id": 101,
          "image": "public/assets/coffee.jpeg",
          "caption": "Morning coffee vibes ☕ #coffeelover",
          "likes": 350,
          "comments": [
            { "id": 1, "user": "friend_01", "comment": "Wow, amazing view!" },
            { "id": 2, "user": "friend_02", "comment": "I want to go there too!" }
          ],
          "createdAt": "2025-11-19T10:30:00Z"
        }
          ]
    },
    {
      "id": 5,
      "username": "geetha_113",
      "fullName": "Geetha",
      "profilePicture": "public/assets/newprofile6.jpeg",
      "bio": "Photography lover 📸 | Traveler ✈️ | Foodie 🍕",
      "followers": 1200,
      "following": 300,
      "posts": [
        {
          "id": 101,
          "image": "public/assets/pasta.jpeg",
          "caption": "Homemade pasta 🍝 #foodie",
          "likes": 350,
          "comments": [
            { "id": 1, "user": "friend_01", "comment": "Wow, amazing view!" },
            { "id": 2, "user": "friend_02", "comment": "I want to go there too!" }
          ],
          "createdAt": "2025-11-19T10:30:00Z"
        }
          ]
    }
    
  ],
  
  "profile":
    {
      "id": 1,
      "username": "d_j2005",
      "fullName": "Divya Jenifer",
      "profilePicture": "public/assets/profile1.jpeg",
      "bio": "Photography lover 📸 | Traveler ✈️ | Foodie 🍕",
      "followers": 1200,
      "following": 300
    },
  
"suggestions": [
  {
    "id": 1,
    "username": "travel_with_anu",
    "fullName": "Anu Sharma",
    "profilePicture": "public/assets/noprofile.jpg",
    "commonFollowers": 12
  },
  {
    "id": 2,
    "username": "foodie_guy",
    "fullName": "Rahul Mehta",
    "profilePicture": "public/assets/profile4.jpg",
    "commonFollowers": 8
  },
  {
    "id": 3,
    "username": "creative_minds",
    "fullName": "Sneha Art",
    "profilePicture": "public/assets/profile5.jpg",
    "commonFollowers": 5
  },
  {
    "id": 4,
    "username": "sneha_holic",
    "fullName": "Sneha Art",
    "profilePicture": "public/assets/noprofile.jpg",
    "commonFollowers": 5
  }
],
"stories":[
  {
      "id": 1,
      "username": "d_j2005",
      "fullName": "Divya Jenifer",
      "profilePicture": "public/assets/profile1.jpeg",
      "image": "public/assets/story1.jpg",
      "storyStatus":true
  },
  
  {
      "id": 2,
      "username": "alexa_rider",
      "fullName": "Alexa Rider",
      "profilePicture": "public/assets/profile2.jpeg",
      "image":"public/assets/story5.jpg",
      "storyStatus":true
  },
   {
      "id": 3,
      "username": "vijay_005",
      "fullName": "vijay",
      "profilePicture": "public/assets/newprofile2.jpeg",
      "image":"public/assets/story2.jpg",
      "storyStatus":true
  },
   {
      "id": 4,
      "username": "Suriya.rolex_1980",
      "fullName": "Suriya",
      "profilePicture": "public/assets/newprofile1.jpeg",
      "image":"public/assets/story4.jpg",
      "storyStatus":true
  },
  {
      "id": 5,
      "username": "geetha_113",
      "fullName": "Geetha",
      "profilePicture": "public/assets/newprofile5.jpeg",
      "image":"public/assets/story3.jpg",
      "storyStatus":false
  },
  {
      "id": 6,
      "username": "peter-the-doc",
      "fullName": "Peter",
      "profilePicture": "public/assets/newprofile3.jpeg",
      "image":"public/assets/story10.jpg",
      "storyStatus":false
  },
  {
      "id": 7,
      "username": "kavi@1902",
      "fullName": "kavitha",
      "profilePicture": "public/assets/newprofile5.jpeg",
      "image":"public/assets/story9.jpg",
      "storyStatus":false
  },
    {
      "id": 8,
      "username": "pookie_004",
      "fullName": "Steve",
      "profilePicture": "public/assets/newprofile4.jpeg",
      "image":"public/assets/story7.jpg",
      "storyStatus":false
  }
]
}
